{
  "https://github.com/apache/tomcat/commit/74b105657ffbd1d1de80455f03446c3bbf30d1f5": {
    "java/org/apache/catalina/servlets/DefaultServlet.java": [
      70,
      1815,
      1814
    ],
    "java/org/apache/catalina/session/FileStore.java": [
      35,
      406,
      409,
      407
    ],
    "java/org/apache/catalina/startup/ContextConfig.java": [
      78,
      765,
      764
    ],
    "java/org/apache/catalina/startup/ExpandWar.java": [
      37,
      102,
      115,
      121,
      209,
      220,
      226,
      101,
      102,
      103,
      104,
      117,
      118,
      124,
      212,
      213,
      214,
      215,
      226,
      227,
      233
    ],
    "java/org/apache/catalina/startup/HostConfig.java": [
      68,
      694,
      695,
      693,
      694
    ],
    "java/org/apache/catalina/util/FileUtil.java": [
      1,
      2,
      3,
      4,
      5,
      6,
      7,
      8,
      9,
      10,
      11,
      12,
      13,
      14,
      15,
      16,
      17,
      18,
      19,
      20,
      21,
      22,
      23,
      24,
      25,
      26,
      27,
      28,
      29,
      30,
      31,
      32,
      33,
      34,
      35,
      36,
      37,
      38,
      39,
      40,
      41,
      42,
      43,
      44,
      45,
      46,
      47,
      48,
      49,
      50
    ]
  },
  "https://github.com/apache/tomcat/commit/800b03140e640f8892f27021e681645e8e320177": {
    "java/org/apache/naming/resources/FileDirContext.java": [
      887,
      888,
      889,
      890,
      891,
      892,
      893,
      894,
      895,
      896,
      897,
      898,
      899,
      916,
      903
    ]
  },
  "https://github.com/apache/tomcat/commit/f9f75c14678b68633f79030ddf4ff827f014cc84": {
    "java/org/apache/tomcat/websocket/WsFrameBase.java": [
      259,
      260,
      261,
      262,
      263,
      264,
      265
    ]
  },
  "https://github.com/apache/tomcat/commit/4c04982870d6e730c38e21e58fb653b7cf723784": {
    "java/org/apache/catalina/websocket/WsFrame.java": [
      87,
      88,
      89,
      90,
      91,
      92
    ]
  },
  "https://github.com/apache/tomcat/commit/53e30390943c18fca0c9e57dbcc14f1c623cfd06": {
    "java/org/apache/catalina/session/FileStore.java": [
      36,
      37,
      48,
      49,
      50,
      51,
      398,
      399,
      402,
      404,
      405,
      406,
      407,
      408,
      409,
      410,
      411,
      392,
      396
    ]
  },
  "https://github.com/apache/tomcat/commit/b191a0d9cf06f4e04257c221bfe41d2b108a9cc8": {
    "java/org/apache/coyote/http11/AbstractHttp11Processor.java": [
      1537,
      1538,
      1539,
      1540,
      1541,
      1542,
      1543,
      1544,
      1537,
      1538,
      1539,
      1540
    ],
    "java/org/apache/tomcat/util/http/parser/TokenList.java": [
      39,
      40,
      41,
      42,
      43,
      44,
      48,
      49,
      53,
      54,
      55,
      58,
      66,
      67,
      68,
      69,
      70,
      71,
      75,
      76,
      77,
      78,
      83,
      96,
      97,
      100,
      101,
      105,
      110,
      111,
      112,
      113,
      39,
      40,
      41,
      45,
      49,
      59,
      60,
      61,
      65,
      82,
      85
    ],
    "test/org/apache/tomcat/util/http/parser/TestTokenList.java": [
      34,
      42,
      52,
      59,
      66,
      76,
      86,
      96,
      106,
      116,
      126,
      131,
      133,
      134,
      135,
      139,
      140,
      141,
      142,
      144,
      145,
      146,
      147,
      148,
      149,
      150,
      151,
      152,
      153,
      154,
      155,
      156,
      157,
      158,
      159,
      160,
      161,
      162,
      163,
      164,
      165,
      166,
      167,
      168,
      169,
      170,
      171,
      172,
      173,
      174,
      175,
      176,
      177,
      178,
      179,
      180,
      181,
      182,
      183,
      184,
      185,
      186,
      187,
      188,
      189,
      190,
      191,
      192,
      193,
      194,
      195,
      196,
      197,
      198,
      199,
      200,
      201,
      34,
      42,
      52,
      59,
      66,
      76,
      86,
      96,
      106,
      116,
      126,
      131,
      133,
      134,
      135,
      139,
      140,
      141
    ]
  },
  "https://github.com/apache/tomcat/commit/702bf15bea292915684d931526d95d4990b2e73d": {
    "java/org/apache/coyote/http11/AbstractHttp11Protocol.java": [
      86,
      88,
      89,
      90,
      95,
      97,
      98,
      99,
      100,
      101,
      102,
      103,
      104,
      105,
      106,
      107,
      108,
      109,
      110,
      111,
      112,
      113,
      114,
      115,
      116,
      117,
      118,
      119,
      120,
      121,
      122,
      123,
      124,
      127,
      128,
      129,
      130,
      131,
      133,
      135,
      86,
      88,
      89,
      90,
      95,
      97,
      98,
      99,
      102,
      103,
      106
    ],
    "java/org/apache/coyote/http11/AbstractInputBuffer.java": [
      111,
      112,
      113,
      114,
      115
    ],
    "java/org/apache/coyote/http11/Http11AprProcessor.java": [
      64,
      73,
      64,
      73
    ],
    "java/org/apache/coyote/http11/Http11AprProtocol.java": [
      302,
      302
    ],
    "java/org/apache/coyote/http11/Http11NioProcessor.java": [
      69,
      79,
      69,
      79
    ],
    "java/org/apache/coyote/http11/Http11NioProtocol.java": [
      267,
      267
    ],
    "java/org/apache/coyote/http11/Http11Processor.java": [
      54,
      63,
      54,
      63
    ],
    "java/org/apache/coyote/http11/Http11Protocol.java": [
      166,
      166
    ],
    "java/org/apache/coyote/http11/InternalAprInputBuffer.java": [
      55,
      67,
      354,
      355,
      364,
      367,
      368,
      369,
      370,
      373,
      374,
      375,
      376,
      465,
      466,
      467,
      468,
      469,
      471,
      472,
      473,
      474,
      475,
      476,
      477,
      478,
      479,
      480,
      481,
      482,
      535,
      536,
      537,
      546,
      547,
      548,
      549,
      551,
      55,
      67,
      364,
      365,
      366,
      367,
      374,
      459,
      460,
      461,
      523,
      525
    ],
    "java/org/apache/coyote/http11/InternalInputBuffer.java": [
      56,
      63,
      306,
      307,
      316,
      319,
      320,
      321,
      325,
      326,
      327,
      328,
      418,
      419,
      420,
      421,
      422,
      424,
      425,
      426,
      427,
      428,
      429,
      430,
      431,
      432,
      433,
      434,
      435,
      436,
      437,
      440,
      506,
      507,
      508,
      517,
      518,
      519,
      520,
      522,
      56,
      63,
      316,
      317,
      318,
      326,
      412,
      413,
      414,
      416,
      417,
      420,
      494,
      496
    ],
    "java/org/apache/coyote/http11/InternalNioInputBuffer.java": [
      103,
      109,
      518,
      519,
      530,
      533,
      534,
      535,
      539,
      540,
      541,
      542,
      642,
      645,
      646,
      648,
      649,
      650,
      651,
      652,
      653,
      654,
      655,
      656,
      657,
      715,
      716,
      717,
      728,
      729,
      730,
      731,
      733,
      103,
      109,
      530,
      531,
      532,
      540,
      638,
      639,
      708,
      710
    ],
    "java/org/apache/tomcat/util/http/MimeHeaders.java": [
      396,
      396
    ],
    "java/org/apache/tomcat/util/http/parser/HttpParser.java": [
      508,
      509,
      510,
      511,
      512,
      513,
      514,
      515,
      516,
      517,
      518
    ],
    "test/org/apache/coyote/http11/TestInternalInputBuffer.java": [
      166,
      172,
      180,
      182,
      183,
      184,
      185,
      186,
      187,
      188,
      189,
      190,
      191,
      192,
      193,
      194,
      195,
      196,
      197,
      198,
      199,
      200,
      201,
      202,
      203,
      204,
      205,
      206,
      207,
      208,
      254,
      255,
      256,
      257,
      258,
      259,
      260,
      261,
      262,
      263,
      264,
      265,
      266,
      267,
      268,
      269,
      270,
      271,
      272,
      273,
      274,
      275,
      276,
      277,
      278,
      279,
      280,
      290,
      291,
      292,
      293,
      294,
      295,
      296,
      297,
      298,
      299,
      300,
      301,
      302,
      303,
      304,
      305,
      306,
      307,
      308,
      309,
      310,
      311,
      312,
      320,
      325,
      333,
      336,
      350,
      351,
      592,
      593,
      594,
      595,
      596,
      597,
      598,
      599,
      600,
      601,
      602,
      603,
      604,
      605,
      606,
      607,
      608,
      609,
      610,
      611,
      612,
      613,
      614,
      615,
      616,
      617,
      618,
      619,
      620,
      621,
      622,
      623,
      624,
      625,
      626,
      627,
      628,
      629,
      630,
      631,
      632,
      633,
      634,
      635,
      636,
      637,
      638,
      639,
      640,
      641,
      642,
      643,
      644,
      645,
      646,
      647,
      648,
      649,
      650,
      651,
      652,
      653,
      654,
      655,
      656,
      657,
      658,
      659,
      660,
      166,
      172,
      180,
      182,
      186,
      229,
      246,
      251,
      259,
      262,
      276,
      277
    ]
  },
  "https://github.com/apache/tomcat/commit/b99fba5bd796d876ea536e83299603443842feba": {
    "java/org/apache/coyote/ajp/AbstractAjpProcessor.java": [
      26,
      27,
      28,
      30,
      31,
      87,
      88,
      89,
      130,
      131,
      132,
      133,
      134,
      135,
      136,
      137,
      346,
      347,
      348,
      349,
      350,
      351,
      352,
      892,
      893,
      894,
      895,
      897,
      898,
      899,
      900,
      901,
      902,
      903,
      904,
      905,
      906,
      907,
      908,
      909,
      910,
      329,
      871
    ],
    "java/org/apache/coyote/ajp/AbstractAjpProtocol.java": [
      19,
      20,
      146,
      147,
      148,
      149,
      150,
      151,
      152,
      153,
      154,
      155,
      156,
      157
    ],
    "java/org/apache/coyote/ajp/AjpAprProtocol.java": [
      157
    ],
    "java/org/apache/coyote/ajp/AjpNioProtocol.java": [
      187
    ],
    "java/org/apache/coyote/ajp/AjpProtocol.java": [
      147
    ],
    "test/org/apache/coyote/ajp/TestAbstractAjpProcessor.java": [
      50
    ]
  },
  "https://github.com/apache/tomcat/commit/40d5d93bd284033cf4a1f77f5492444f83d803e2": {
    "java/org/apache/coyote/ajp/AbstractAjpProcessor.java": [
      303,
      305,
      306,
      307,
      308,
      309,
      310,
      312,
      841,
      944,
      945,
      946,
      962,
      305,
      834,
      937,
      938,
      939,
      955
    ],
    "java/org/apache/coyote/ajp/AbstractAjpProtocol.java": [
      98,
      99,
      100,
      101,
      102,
      103,
      104,
      105,
      106,
      107,
      108,
      109,
      110,
      115,
      116,
      117,
      119,
      121,
      122,
      123,
      124,
      125,
      126,
      127,
      128,
      129,
      130,
      131,
      132,
      133,
      134,
      135,
      136,
      137,
      138,
      139,
      140,
      190,
      191,
      192,
      193,
      194,
      195,
      196,
      197,
      198,
      199,
      200,
      201,
      104
    ],
    "java/org/apache/coyote/ajp/AjpAprProtocol.java": [
      153,
      153
    ],
    "java/org/apache/coyote/ajp/AjpNioProtocol.java": [
      183,
      183
    ],
    "java/org/apache/coyote/ajp/AjpProtocol.java": [
      143,
      143
    ],
    "test/org/apache/coyote/ajp/TestAbstractAjpProcessor.java": [
      33,
      37,
      43,
      44,
      45,
      46,
      47,
      48,
      49,
      50,
      51
    ]
  },
  "https://github.com/apache/tomcat/commit/f7180bafc74cb1250c9e9287b68a230f0e1f4645": {
    "java/org/apache/coyote/ajp/AbstractAjpProtocol.java": [
      207,
      214,
      207,
      214
    ]
  },
  "https://github.com/apache/tomcat/commit/0d633e72ebc7b3c242d0081c23bba5e4dacd9b72": {
    "java/org/apache/coyote/ajp/AjpAprProtocol.java": [
      23,
      65
    ],
    "java/org/apache/coyote/ajp/AjpNioProtocol.java": [
      26,
      60
    ],
    "java/org/apache/coyote/ajp/AjpProtocol.java": [
      25,
      61
    ],
    "java/org/apache/tomcat/util/compat/Jre7Compat.java": [
      23,
      60,
      77,
      97,
      125,
      361,
      362,
      363,
      364,
      365,
      366,
      367,
      368,
      369,
      370,
      371,
      372,
      373,
      374
    ],
    "java/org/apache/tomcat/util/compat/JreCompat.java": [
      24,
      27,
      237,
      238,
      239,
      240,
      241,
      242,
      243,
      244,
      245,
      246,
      247,
      248,
      249,
      250,
      251,
      252,
      253,
      254,
      255,
      256,
      257,
      258,
      259,
      260,
      261,
      262
    ]
  },
  "https://github.com/apache/tomcat/commit/ab72a106fe5d992abddda954e30849d7cf8cc583": {
    "java/org/apache/catalina/authenticator/AuthenticatorBase.java": [
      917,
      918,
      921,
      917,
      918
    ],
    "java/org/apache/catalina/authenticator/Constants.java": [
      111,
      112,
      114
    ],
    "java/org/apache/catalina/authenticator/FormAuthenticator.java": [
      174,
      206,
      207,
      208,
      209,
      210,
      211,
      296,
      491,
      156,
      157,
      158,
      159,
      178,
      180,
      197,
      198,
      199,
      200,
      201,
      202,
      203,
      204,
      205,
      206,
      305,
      306,
      307,
      308,
      309,
      310,
      505,
      535
    ]
  },
  "https://github.com/apache/tomcat/commit/bef3f40400243348d12f4abfe9b413f43897c02b": {
    "java/org/apache/catalina/mbeans/JmxRemoteLifecycleListener.java": [
      28,
      30,
      31,
      324,
      325,
      326,
      327,
      328,
      329,
      330,
      331,
      332,
      333,
      493,
      494,
      495,
      496,
      497,
      498,
      499,
      500,
      501,
      502,
      503,
      504,
      505,
      506,
      507,
      508,
      509,
      510,
      511,
      512,
      513,
      514,
      515,
      516,
      517,
      518,
      519,
      520,
      521,
      522,
      523,
      524,
      525,
      526,
      527,
      30,
      31,
      303,
      304,
      305,
      306,
      307,
      308,
      309,
      310,
      311,
      312,
      313,
      314,
      335,
      343,
      344,
      345,
      346
    ]
  },
  "https://github.com/apache/tomcat/commit/7f0221b904956359f2d739aa3a2b53f8c12ed8c7": {
    "java/org/apache/catalina/servlets/CGIServlet.java": [
      56,
      252,
      253,
      254,
      259,
      260,
      261,
      262,
      263,
      264,
      265,
      266,
      332,
      333,
      334,
      335,
      336,
      337,
      338,
      339,
      437,
      438,
      439,
      440,
      441,
      442,
      443,
      444,
      848,
      850,
      851,
      852,
      853,
      854,
      855,
      856,
      857,
      858,
      1129
    ]
  },
  "https://github.com/apache/tomcat/commit/44ec74c44dcd05cd7e90967c04d40b51440ecd7e": {
    "java/org/apache/catalina/ssi/SSIPrintenv.java": [
      25,
      46,
      25,
      46,
      47
    ]
  }
}